{
  "status": "ok",
  "scraped_at": "2025-08-16T16:43:47.279Z",
  "sources": [
    "https://t.me/s/RealRate2000"
  ],
  "ttl_minutes": 60,
  "config": {
    "need_min_samples": 5,
    "trim_frac": 0.2,
    "pct_spread_max": 1,
    "soft_guard_pct": 20,
    "soft_guard_ref_source": "baseline",
    "soft_guard_ref_value": 90000
  },
  "counts": {
    "per_source": [
      {
        "source": "https://t.me/s/RealRate2000",
        "raw_blocks": 20,
        "candidates": 12,
        "removed": 14,
        "candidates_usd": 6,
        "candidates_eur": 6
      }
    ],
    "candidates_all": 12,
    "deduped": 0,
    "removed_all": 14,
    "by_currency": {
      "USD": 6,
      "EUR": 6
    }
  },
  "summary": {
    "used_n": 0,
    "min": 91600,
    "max": 107000,
    "median": 92000,
    "spread_pct": 16.739,
    "estimate": null,
    "method": null
  },
  "summary_usd": {
    "used_n": 0,
    "min": 91600,
    "max": 107000,
    "median": 92000,
    "spread_pct": 16.739,
    "estimate": null,
    "method": null
  },
  "summary_eur": {
    "used_n": 0,
    "min": 91600,
    "max": 107000,
    "median": 92000,
    "spread_pct": 16.739,
    "estimate": null,
    "method": null
  },
  "samples_used_usd": [],
  "samples_used_eur": [],
  "removed_examples": []
}